copy_env/__init__.py
copy_env-0.1.2.dist-info/LICENSE.txt
copy_env-0.1.2.dist-info/METADATA
copy_env-0.1.2.dist-info/WHEEL
copy_env-0.1.2.dist-info/top_level.txt
copy_env-0.1.2.dist-info/RECORD
