Metadata-Version: 2.1
Name: copy-env
Version: 0.1.2
Summary: A package to copy environment requirements from one venv to another.
Home-page: https://github.com/deschman/reporting
Author: Dan Eschman
Author-email: deschman007@gmail.com
License: UNKNOWN
Platform: UNKNOWN
Classifier: Natural Language :: English
Classifier: Topic :: Software Development :: Libraries :: Python Modules
Classifier: Programming Language :: Python :: 3
Classifier: Development Status :: 3 - Alpha
Classifier: License :: OSI Approved :: GNU General Public License v3 (GPLv3)
Requires-Python: ~=3.8
Requires-Dist: pytest
Requires-Dist: pytest-virtualenv
